{
    "basics": {
      "name": "Abby Gottlich",
      "label": "Developer, Designer",
      "picture": "https://secure.gravatar.com/avatar/8467b459fa717a7bd10f4ada1daaedbe",
      "email": "abby.gottlich@gmail.com",
      "website": "http://www.abbygottlich.dev/",
      "summary": "Developer-Designer Hybrid, Seeking a Job that Allows Me to do Both",
      "phone": "972.948.0392",
      "location": {
        "city": "Dallas",
        "region": "Texas"
      },
      "profiles": [
        {
          "network": "PDF Resume",
          "username": "Abby Gottlich",
          "url": "https://github.com/abbygottlich/resume"
        },
        {
          "network": "GitHub",
          "username": "abbygottlich",
          "url": "https://github.com/abbygottlich"
        },
        {
          "network": "LinkedIn",
          "username": "abbygottlich",
          "url": "https://www.linkedin.com/in/abbygottlich/"
        }
      ]
    },
    "work": [
      {
        "company": "Mutual Mobile",
        "position": "Web Developer Intern",
        "website": "https://mutualmobile.com/",
        "startDate": "2018-10-23",
        "endDate": "2019-02-28",
        "summary": "Worked directly with senior level developers and UX Designers to program a multi-faceted web application, completing tasks to meet client goals.",
        "highlights": [
          "Used HTML5, CSS3, JavaScript, and AngularJS",
          "In charge of all styling for new user flow built from scratch",
          "Practiced an agile work environment through sprint planning"
        ]
      },
      {
        "company": "Oddly Natural",
        "position": "Director of Graphic Design",
        "website": "https://www.liveoddlynatural.com/",
        "startDate": "2017-09-02",
        "endDate": "2018-10-20",
        "summary": "Developed brand identities for new and existing companies.",
        "highlights": [
          "Designed logos and websites",
          "Worked hand-in-hand with the developer to create an effective online presence to meet client goals",
          "Enhanced the online presence of clients in the form of social media graphics, utilizing Photoshop and Illustrator",
          "Successfully promoted client events through poster and billboard design, utilizing InDesign, and incorporating hand-drawn illustrations"
        ]
      },
      {
        "company": "Fort Stockton Independent School District",
        "position": "Webmaster",
        "website": "https://www.fsisd.net/",
        "startDate": "2016-11-09",
        "endDate": "2017-08-22",
        "summary": "Successfully transformed a dated, disorganized website into an intuitive, modern Content Management System.",
        "highlights": [
          "Utilized information architecture, card sorting, and communication skills",
          "Trained all teachers and staff members to edit/manage their own personal webpage",
          "Engaged the community in the District’s strengthened online social media presence by photographing all school events"
        ]
      },
      {
        "company": "MasonBaronet",
        "position": "Creative Intern",
        "website": "http://masonbaronet.com/",
        "startDate": "2015-05-10",
        "endDate": "2015-08-20",
        "summary": "Obtained design skills and an understanding of creative direction by designing special collateral for office functions.",
        "highlights": [
          "Used Illustrator, Photoshop, and InDesign",
          "Gained skills in communication and collaboration through daily team meetings and regularly reporting to the Creative Director"
        ]
      }
    ],
    "projects": [
      {
        "name": "Feast Finder",
        "description": "Random Restaurant Generator",
        "highlights": [
          "Creator and current maintainer",
          "Built with React.js, Express.js, MongoDB, and Mongoose",
          "Utilizes authentication and React-Redux"
        ],
        "keywords": [
          "React",
          "Express",
          "MongoDB",
          "Mongoose",
          "React-Redux",
          "Authentication"
        ],
        "url": "https://github.com/abbygottlich/feast-finder-app",
        "roles": [
          "Creator",
          "Maintainer"
        ],
        "type": "Web Application"
      }
    ],
    "skills": [
      {
        "name": "Languages",
        "keywords":
        [
          "JavaScript/Node.js",
          "AngularJS"
        ]
      },
      {
        "name": "Web Development",
        "keywords": [
          "HTML/CSS",
          "JavaScript/jQuery",
          "Express/Node.js",
          "React + Redux",
          "Express",
          "Mongoose",
          "MongoDB",
          "Authorization/Authentication",
          "Responsive/Mobile Development"
        ]
      },
      {
        "name": "Technologies",
        "keywords": [
          "Heroku",
          "Git/GitHub",
          "REST APIs"
        ]
      }
    ]
  }